MANIFEST.in
README.md
converter.py
publish_data_source.py
setup.cfg
setup.py
tableau_hyper_management/config.json
tableau_hyper_management/sample---user-settings.json
tableau_hyper_management.egg-info/PKG-INFO
tableau_hyper_management.egg-info/SOURCES.txt
tableau_hyper_management.egg-info/dependency_links.txt
tableau_hyper_management.egg-info/requires.txt
tableau_hyper_management.egg-info/top_level.txt