Metadata-Version: 2.1
Name: tableau-hyper-management
Version: 1.2.16
Summary: Wrapper to ease data management into Tableau Hyper format from CSV files
Home-page: https://github.com/danielgp/tableau-hyper-management/releases
Author: Daniel Popiniuc
Author-email: danielpopiniuc@gmail.com
License: LGPL3
Project-URL: Documentation, https://github.com/danielgp/tableau-hyper-management/blob/master/README.md
Project-URL: Issue Tracker, https://github.com/danielgp/tableau-hyper-management/issues?q=is%3Aissue+is%3Aopen+sort%3Aupdated-desc
Project-URL: Source Code, https://github.com/danielgp/tableau-hyper-management
Keywords: tableau,hyper,csv
Platform: UNKNOWN
Classifier: Development Status :: 5 - Production/Stable
Classifier: Environment :: Console
Classifier: Intended Audience :: Developers
Classifier: Intended Audience :: Information Technology
Classifier: Intended Audience :: System Administrators
Classifier: License :: OSI Approved :: GNU Lesser General Public License v3 (LGPLv3)
Classifier: Natural Language :: English
Classifier: Programming Language :: Python :: 3.6
Classifier: Programming Language :: Python :: 3.7
Classifier: Programming Language :: Python :: 3.8
Classifier: Topic :: Scientific/Engineering :: Information Analysis
Requires-Python: >=3.6
